clctool.py
CLCTool-8.6.dist-info/LICENSE.md
CLCTool-8.6.dist-info/METADATA
CLCTool-8.6.dist-info/WHEEL
CLCTool-8.6.dist-info/entry_points.txt
CLCTool-8.6.dist-info/top_level.txt
CLCTool-8.6.dist-info/RECORD
