Metadata-Version: 2.1
Name: CLCTool
Version: 8.6
License-File: LICENSE.md
Requires-Dist: PyYAML
